[
  {
    "viewport": "1920x1080",
    "touch": false,
    "device": {
      "maxTouchPoints": 0,
      "primaryCoarse": false,
      "finePointer": true,
      "domVirtualControls": 0
    },
    "canvasHitMode": "Godot probe center + document.elementFromPoint(canvas host)",
    "main": {
      "achievements": {
        "center_x": 163,
        "center_y": 308,
        "exists": true,
        "height": 48,
        "visible": true,
        "width": 270,
        "x": 28,
        "y": 284
      },
      "meta": {
        "center_x": 163,
        "center_y": 248,
        "exists": true,
        "height": 48,
        "visible": true,
        "width": 270,
        "x": 28,
        "y": 224
      },
      "seed_input": {
        "center_x": 103,
        "center_y": 426,
        "exists": true,
        "height": 48,
        "visible": true,
        "width": 150,
        "x": 28,
        "y": 402
      },
      "seed_start": {
        "center_x": 244,
        "center_y": 426,
        "exists": true,
        "height": 48,
        "visible": true,
        "width": 108,
        "x": 190,
        "y": 402
      },
      "settings": {
        "center_x": 163,
        "center_y": 368,
        "exists": true,
        "height": 48,
        "visible": true,
        "width": 270,
        "x": 28,
        "y": 344
      },
      "side_close": {
        "center_x": 1841,
        "center_y": 192,
        "exists": true,
        "height": 48,
        "visible": false,
        "width": 82,
        "x": 1800,
        "y": 168
      },
      "side_panel": {
        "center_x": 1632,
        "center_y": 414,
        "exists": true,
        "height": 520,
        "visible": false,
        "width": 520,
        "x": 1372,
        "y": 154
      },
      "start": {
        "center_x": 163,
        "center_y": 188,
        "exists": true,
        "height": 48,
        "visible": true,
        "width": 270,
        "x": 28,
        "y": 164
      }
    },
    "pause": {
      "active_ability": {
        "center_x": 1865,
        "center_y": 1021,
        "exists": true,
        "height": 62,
        "visible": false,
        "width": 62,
        "x": 1834,
        "y": 990
      },
      "pause": {
        "center_x": 1869,
        "center_y": 34,
        "exists": true,
        "height": 48,
        "visible": true,
        "width": 74,
        "x": 1832,
        "y": 10
      },
      "pause_achievements_tab": {
        "center_x": 966,
        "center_y": 309,
        "exists": true,
        "height": 48,
        "visible": true,
        "width": 164,
        "x": 884,
        "y": 285
      },
      "pause_overlay": {
        "center_x": 960,
        "center_y": 540,
        "exists": true,
        "height": 610,
        "visible": true,
        "width": 540,
        "x": 690,
        "y": 235
      },
      "pause_resume": {
        "center_x": 960,
        "center_y": 805,
        "exists": true,
        "height": 48,
        "visible": true,
        "width": 160,
        "x": 880,
        "y": 781
      },
      "pause_run_tab": {
        "center_x": 1142,
        "center_y": 309,
        "exists": true,
        "height": 48,
        "visible": true,
        "width": 164,
        "x": 1060,
        "y": 285
      },
      "pause_settings_tab": {
        "center_x": 790,
        "center_y": 309,
        "exists": true,
        "height": 48,
        "visible": true,
        "width": 164,
        "x": 708,
        "y": 285
      },
      "virtual_joystick": {
        "center_x": 95.8399963378906,
        "center_y": 984.160034179688,
        "exists": true,
        "height": 163.679992675781,
        "visible": false,
        "width": 163.679992675781,
        "x": 14,
        "y": 902.320007324219
      }
    },
    "status": "pass"
  },
  {
    "viewport": "1440x780",
    "touch": false,
    "device": {
      "maxTouchPoints": 0,
      "primaryCoarse": false,
      "finePointer": true,
      "domVirtualControls": 0
    },
    "canvasHitMode": "Godot probe center + document.elementFromPoint(canvas host)",
    "main": {
      "achievements": {
        "center_x": 163,
        "center_y": 308,
        "exists": true,
        "height": 48,
        "visible": true,
        "width": 270,
        "x": 28,
        "y": 284
      },
      "meta": {
        "center_x": 163,
        "center_y": 248,
        "exists": true,
        "height": 48,
        "visible": true,
        "width": 270,
        "x": 28,
        "y": 224
      },
      "seed_input": {
        "center_x": 103,
        "center_y": 426,
        "exists": true,
        "height": 48,
        "visible": true,
        "width": 150,
        "x": 28,
        "y": 402
      },
      "seed_start": {
        "center_x": 244,
        "center_y": 426,
        "exists": true,
        "height": 48,
        "visible": true,
        "width": 108,
        "x": 190,
        "y": 402
      },
      "settings": {
        "center_x": 163,
        "center_y": 368,
        "exists": true,
        "height": 48,
        "visible": true,
        "width": 270,
        "x": 28,
        "y": 344
      },
      "side_close": {
        "center_x": 1361,
        "center_y": 192,
        "exists": true,
        "height": 48,
        "visible": false,
        "width": 82,
        "x": 1320,
        "y": 168
      },
      "side_panel": {
        "center_x": 1152,
        "center_y": 414,
        "exists": true,
        "height": 520,
        "visible": false,
        "width": 520,
        "x": 892,
        "y": 154
      },
      "start": {
        "center_x": 163,
        "center_y": 188,
        "exists": true,
        "height": 48,
        "visible": true,
        "width": 270,
        "x": 28,
        "y": 164
      }
    },
    "pause": {
      "active_ability": {
        "center_x": 1385,
        "center_y": 721,
        "exists": true,
        "height": 62,
        "visible": false,
        "width": 62,
        "x": 1354,
        "y": 690
      },
      "pause": {
        "center_x": 1389,
        "center_y": 34,
        "exists": true,
        "height": 48,
        "visible": true,
        "width": 74,
        "x": 1352,
        "y": 10
      },
      "pause_achievements_tab": {
        "center_x": 726,
        "center_y": 159,
        "exists": true,
        "height": 48,
        "visible": true,
        "width": 164,
        "x": 644,
        "y": 135
      },
      "pause_overlay": {
        "center_x": 720,
        "center_y": 390,
        "exists": true,
        "height": 610,
        "visible": true,
        "width": 540,
        "x": 450,
        "y": 85
      },
      "pause_resume": {
        "center_x": 720,
        "center_y": 655,
        "exists": true,
        "height": 48,
        "visible": true,
        "width": 160,
        "x": 640,
        "y": 631
      },
      "pause_run_tab": {
        "center_x": 902,
        "center_y": 159,
        "exists": true,
        "height": 48,
        "visible": true,
        "width": 164,
        "x": 820,
        "y": 135
      },
      "pause_settings_tab": {
        "center_x": 550,
        "center_y": 159,
        "exists": true,
        "height": 48,
        "visible": true,
        "width": 164,
        "x": 468,
        "y": 135
      },
      "virtual_joystick": {
        "center_x": 95.8399963378906,
        "center_y": 684.160034179688,
        "exists": true,
        "height": 163.679992675781,
        "visible": false,
        "width": 163.679992675781,
        "x": 14,
        "y": 602.320007324219
      }
    },
    "status": "pass"
  },
  {
    "viewport": "1366x600",
    "touch": false,
    "device": {
      "maxTouchPoints": 0,
      "primaryCoarse": false,
      "finePointer": true,
      "domVirtualControls": 0
    },
    "canvasHitMode": "Godot probe center + document.elementFromPoint(canvas host)",
    "main": {
      "achievements": {
        "center_x": 163,
        "center_y": 308,
        "exists": true,
        "height": 48,
        "visible": true,
        "width": 270,
        "x": 28,
        "y": 284
      },
      "meta": {
        "center_x": 163,
        "center_y": 248,
        "exists": true,
        "height": 48,
        "visible": true,
        "width": 270,
        "x": 28,
        "y": 224
      },
      "seed_input": {
        "center_x": 103,
        "center_y": 426,
        "exists": true,
        "height": 48,
        "visible": true,
        "width": 150,
        "x": 28,
        "y": 402
      },
      "seed_start": {
        "center_x": 244,
        "center_y": 426,
        "exists": true,
        "height": 48,
        "visible": true,
        "width": 108,
        "x": 190,
        "y": 402
      },
      "settings": {
        "center_x": 163,
        "center_y": 368,
        "exists": true,
        "height": 48,
        "visible": true,
        "width": 270,
        "x": 28,
        "y": 344
      },
      "side_close": {
        "center_x": 1287,
        "center_y": 192,
        "exists": true,
        "height": 48,
        "visible": false,
        "width": 82,
        "x": 1246,
        "y": 168
      },
      "side_panel": {
        "center_x": 1078,
        "center_y": 363,
        "exists": true,
        "height": 418,
        "visible": false,
        "width": 520,
        "x": 818,
        "y": 154
      },
      "start": {
        "center_x": 163,
        "center_y": 188,
        "exists": true,
        "height": 48,
        "visible": true,
        "width": 270,
        "x": 28,
        "y": 164
      }
    },
    "pause": {
      "active_ability": {
        "center_x": 1311,
        "center_y": 541,
        "exists": true,
        "height": 62,
        "visible": false,
        "width": 62,
        "x": 1280,
        "y": 510
      },
      "pause": {
        "center_x": 1315,
        "center_y": 34,
        "exists": true,
        "height": 48,
        "visible": true,
        "width": 74,
        "x": 1278,
        "y": 10
      },
      "pause_achievements_tab": {
        "center_x": 689,
        "center_y": 96,
        "exists": true,
        "height": 48,
        "visible": true,
        "width": 164,
        "x": 607,
        "y": 72
      },
      "pause_overlay": {
        "center_x": 683,
        "center_y": 300,
        "exists": true,
        "height": 556,
        "visible": true,
        "width": 540,
        "x": 413,
        "y": 22
      },
      "pause_resume": {
        "center_x": 683,
        "center_y": 538,
        "exists": true,
        "height": 48,
        "visible": true,
        "width": 160,
        "x": 603,
        "y": 514
      },
      "pause_run_tab": {
        "center_x": 865,
        "center_y": 96,
        "exists": true,
        "height": 48,
        "visible": true,
        "width": 164,
        "x": 783,
        "y": 72
      },
      "pause_settings_tab": {
        "center_x": 513,
        "center_y": 96,
        "exists": true,
        "height": 48,
        "visible": true,
        "width": 164,
        "x": 431,
        "y": 72
      },
      "virtual_joystick": {
        "center_x": 95.8399963378906,
        "center_y": 504.160003662109,
        "exists": true,
        "height": 163.679992675781,
        "visible": false,
        "width": 163.679992675781,
        "x": 14,
        "y": 422.320007324219
      }
    },
    "status": "pass"
  },
  {
    "viewport": "1280x640",
    "touch": false,
    "device": {
      "maxTouchPoints": 0,
      "primaryCoarse": false,
      "finePointer": true,
      "domVirtualControls": 0
    },
    "canvasHitMode": "Godot probe center + document.elementFromPoint(canvas host)",
    "main": {
      "achievements": {
        "center_x": 163,
        "center_y": 308,
        "exists": true,
        "height": 48,
        "visible": true,
        "width": 270,
        "x": 28,
        "y": 284
      },
      "meta": {
        "center_x": 163,
        "center_y": 248,
        "exists": true,
        "height": 48,
        "visible": true,
        "width": 270,
        "x": 28,
        "y": 224
      },
      "seed_input": {
        "center_x": 103,
        "center_y": 426,
        "exists": true,
        "height": 48,
        "visible": true,
        "width": 150,
        "x": 28,
        "y": 402
      },
      "seed_start": {
        "center_x": 244,
        "center_y": 426,
        "exists": true,
        "height": 48,
        "visible": true,
        "width": 108,
        "x": 190,
        "y": 402
      },
      "settings": {
        "center_x": 163,
        "center_y": 368,
        "exists": true,
        "height": 48,
        "visible": true,
        "width": 270,
        "x": 28,
        "y": 344
      },
      "side_close": {
        "center_x": 1201,
        "center_y": 192,
        "exists": true,
        "height": 48,
        "visible": false,
        "width": 82,
        "x": 1160,
        "y": 168
      },
      "side_panel": {
        "center_x": 992,
        "center_y": 383,
        "exists": true,
        "height": 458,
        "visible": false,
        "width": 520,
        "x": 732,
        "y": 154
      },
      "start": {
        "center_x": 163,
        "center_y": 188,
        "exists": true,
        "height": 48,
        "visible": true,
        "width": 270,
        "x": 28,
        "y": 164
      }
    },
    "pause": {
      "active_ability": {
        "center_x": 1225,
        "center_y": 581,
        "exists": true,
        "height": 62,
        "visible": false,
        "width": 62,
        "x": 1194,
        "y": 550
      },
      "pause": {
        "center_x": 1229,
        "center_y": 34,
        "exists": true,
        "height": 48,
        "visible": true,
        "width": 74,
        "x": 1192,
        "y": 10
      },
      "pause_achievements_tab": {
        "center_x": 646,
        "center_y": 96,
        "exists": true,
        "height": 48,
        "visible": true,
        "width": 164,
        "x": 564,
        "y": 72
      },
      "pause_overlay": {
        "center_x": 640,
        "center_y": 320,
        "exists": true,
        "height": 596,
        "visible": true,
        "width": 540,
        "x": 370,
        "y": 22
      },
      "pause_resume": {
        "center_x": 640,
        "center_y": 578,
        "exists": true,
        "height": 48,
        "visible": true,
        "width": 160,
        "x": 560,
        "y": 554
      },
      "pause_run_tab": {
        "center_x": 822,
        "center_y": 96,
        "exists": true,
        "height": 48,
        "visible": true,
        "width": 164,
        "x": 740,
        "y": 72
      },
      "pause_settings_tab": {
        "center_x": 470,
        "center_y": 96,
        "exists": true,
        "height": 48,
        "visible": true,
        "width": 164,
        "x": 388,
        "y": 72
      },
      "virtual_joystick": {
        "center_x": 95.8399963378906,
        "center_y": 544.160034179688,
        "exists": true,
        "height": 163.679992675781,
        "visible": false,
        "width": 163.679992675781,
        "x": 14,
        "y": 462.320007324219
      }
    },
    "status": "pass"
  },
  {
    "viewport": "390x844",
    "touch": true,
    "device": {
      "maxTouchPoints": 1,
      "primaryCoarse": true,
      "finePointer": false,
      "domVirtualControls": 0
    },
    "canvasHitMode": "Godot probe center + document.elementFromPoint(canvas host)",
    "main": {
      "achievements": {
        "center_x": 195,
        "center_y": 500,
        "exists": true,
        "height": 76,
        "visible": true,
        "width": 351,
        "x": 19.5,
        "y": 462
      },
      "meta": {
        "center_x": 195,
        "center_y": 408,
        "exists": true,
        "height": 76,
        "visible": true,
        "width": 351,
        "x": 19.5,
        "y": 370
      },
      "seed_input": {
        "center_x": 121,
        "center_y": 672,
        "exists": true,
        "height": 76,
        "visible": true,
        "width": 203,
        "x": 19.5,
        "y": 634
      },
      "seed_start": {
        "center_x": 304.5,
        "center_y": 672,
        "exists": true,
        "height": 76,
        "visible": true,
        "width": 132,
        "x": 238.5,
        "y": 634
      },
      "settings": {
        "center_x": 195,
        "center_y": 592,
        "exists": true,
        "height": 76,
        "visible": true,
        "width": 351,
        "x": 19.5,
        "y": 554
      },
      "side_close": {
        "center_x": 298,
        "center_y": 198,
        "exists": true,
        "height": 76,
        "visible": false,
        "width": 104,
        "x": 246,
        "y": 160
      },
      "side_panel": {
        "center_x": 195,
        "center_y": 486,
        "exists": true,
        "height": 680,
        "visible": false,
        "width": 354,
        "x": 18,
        "y": 146
      },
      "start": {
        "center_x": 195,
        "center_y": 316,
        "exists": true,
        "height": 76,
        "visible": true,
        "width": 351,
        "x": 19.5,
        "y": 278
      }
    },
    "pause": {
      "active_ability": {
        "center_x": 322,
        "center_y": 764,
        "exists": true,
        "height": 92,
        "visible": true,
        "width": 92,
        "x": 276,
        "y": 718
      },
      "pause": {
        "center_x": 322,
        "center_y": 64,
        "exists": true,
        "height": 76,
        "visible": true,
        "width": 104,
        "x": 270,
        "y": 26
      },
      "pause_achievements_tab": {
        "center_x": 205,
        "center_y": 158,
        "exists": true,
        "height": 52,
        "visible": true,
        "width": 106,
        "x": 152,
        "y": 132
      },
      "pause_overlay": {
        "center_x": 195,
        "center_y": 422,
        "exists": true,
        "height": 680,
        "visible": true,
        "width": 366,
        "x": 12,
        "y": 82
      },
      "pause_resume": {
        "center_x": 195,
        "center_y": 730,
        "exists": true,
        "height": 76,
        "visible": true,
        "width": 190,
        "x": 100,
        "y": 692
      },
      "pause_run_tab": {
        "center_x": 327,
        "center_y": 158,
        "exists": true,
        "height": 52,
        "visible": true,
        "width": 106,
        "x": 274,
        "y": 132
      },
      "pause_settings_tab": {
        "center_x": 83,
        "center_y": 158,
        "exists": true,
        "height": 52,
        "visible": true,
        "width": 106,
        "x": 30,
        "y": 132
      },
      "virtual_joystick": {
        "center_x": 134.063995361328,
        "center_y": 699.93603515625,
        "exists": true,
        "height": 232.128005981445,
        "visible": true,
        "width": 232.128005981445,
        "x": 18,
        "y": 583.872009277344
      }
    },
    "status": "pass"
  }
]
